qoqo_mock/DEPENDENCIES
qoqo_mock/__init__.py
qoqo_mock/backend/__init__.py
qoqo_mock/backend/mocked_backend.py
qoqo_mock/interface/__init__.py
qoqo_mock/interface/mocked_interface.py
qoqo_mock-0.5.10.dist-info/licenses/LICENSE
qoqo_mock-0.5.10.dist-info/METADATA
qoqo_mock-0.5.10.dist-info/WHEEL
qoqo_mock-0.5.10.dist-info/top_level.txt
qoqo_mock-0.5.10.dist-info/RECORD
