Metadata-Version: 2.4
Name: qoqo_mock
Version: 0.5.10
Author-email: HQS Quantum Simulation GmbH <info@quantumsimulations.de>
License: Apache-2.0
License-File: LICENSE
Requires-Dist: qoqo_calculator_pyo3>=1.7
Requires-Dist: qoqo>=1.21
Requires-Dist: numpy
Provides-Extra: tests
Requires-Dist: pytest; extra == "tests"
Requires-Dist: pytest-cov; extra == "tests"
Provides-Extra: dev
Requires-Dist: flake8; extra == "dev"
Requires-Dist: flake8-bugbear; extra == "dev"
Requires-Dist: flake8-pyproject; extra == "dev"
Requires-Dist: flake8-pydocstyle; extra == "dev"
Requires-Dist: flake8-bandit; extra == "dev"
Requires-Dist: flake8-pyproject; extra == "dev"
Requires-Dist: darglint; extra == "dev"
Requires-Dist: bandit; extra == "dev"
Requires-Dist: mypy; extra == "dev"
Requires-Dist: black; extra == "dev"
Requires-Dist: ruff; extra == "dev"
Provides-Extra: docs
Requires-Dist: sphinx>=2.1; extra == "docs"
Requires-Dist: nbsphinx; extra == "docs"
Requires-Dist: pygments; extra == "docs"
Requires-Dist: recommonmark; extra == "docs"
Requires-Dist: myst_parser; extra == "docs"
Requires-Dist: sphinx_rtd_theme; extra == "docs"
Requires-Dist: tomli; extra == "docs"
Dynamic: license-file
